shuffle_graph_package/__init__.py
shuffle_graph_package/shuffle_graph_module.py
shuffle_graph-2.2.0.dist-info/LICENSE
shuffle_graph-2.2.0.dist-info/METADATA
shuffle_graph-2.2.0.dist-info/WHEEL
shuffle_graph-2.2.0.dist-info/top_level.txt
shuffle_graph-2.2.0.dist-info/RECORD
