Metadata-Version: 2.1
Name: shuffle-graph
Version: 2.2.0
Summary: Graph shuffling package in python.
Home-page: https://github.com/fsssosei/shuffle_graph
Author: sosei
Author-email: fss.sosei@gmail.com
License: GNU Affero General Public License v3
Keywords: Graph,Shuffle
Platform: UNKNOWN
Classifier: Development Status :: 5 - Production/Stable
Classifier: License :: OSI Approved :: GNU Affero General Public License v3
Classifier: Programming Language :: Python :: 3.8
Requires-Python: >=3.8
Requires-Dist: networkx (>=2.5)
Requires-Dist: complete-shuffle (>=1.1.2)
